gguf_core/__init__.py
gguf_core/logo.png
gguf_core-0.0.66.dist-info/entry_points.txt
gguf_core-0.0.66.dist-info/LICENSE
gguf_core-0.0.66.dist-info/WHEEL
gguf_core-0.0.66.dist-info/METADATA
gguf_core-0.0.66.dist-info/RECORD
