Metadata-Version: 2.1
Name: gguf-core
Version: 0.0.66
Summary: a simple way to interact llama with gguf
Author-email: calcuis <info@calcu.io>
Classifier: License :: OSI Approved :: MIT License
Requires-Dist: llama-core >=0.3.3
Project-URL: Homepage, https://gguf.us
Project-URL: Issues, https://github.com/calcuis/gguf-core/issues
Project-URL: Repository, https://github.com/calcuis/gguf-core
